nachos-0.1.14.dist-info/METADATA
nachos-0.1.14.dist-info/WHEEL
nachos-0.1.14.dist-info/entry_points.txt
nachos-0.1.14.dist-info/licenses/LICENSE
nagioscli/__init__.py
nagioscli/__main__.py
nagioscli/cli/__init__.py
nagioscli/cli/commands/__init__.py
nagioscli/cli/commands/ack.py
nagioscli/cli/commands/check.py
nagioscli/cli/commands/hosts.py
nagioscli/cli/commands/login.py
nagioscli/cli/commands/problems.py
nagioscli/cli/commands/services.py
nagioscli/cli/commands/status.py
nagioscli/cli/decorators.py
nagioscli/cli/handlers.py
nagioscli/core/__init__.py
nagioscli/core/auth.py
nagioscli/core/client.py
nagioscli/core/config.py
nagioscli/core/exceptions.py
nagioscli/core/models.py
nagioscli/services/__init__.py
nachos-0.1.14.dist-info/RECORD
