Metadata-Version: 2.1
Name: nachos
Version: 0.1.14
Summary: A CLI tool to manage Nagios Core via HTTP REST API
Keywords: nagios,monitoring,cli,api,devops
Author-Email: lduchosal <lduchosal@github.com>
License: MIT
Classifier: Development Status :: 4 - Beta
Classifier: Intended Audience :: System Administrators
Classifier: License :: OSI Approved :: MIT License
Classifier: Operating System :: OS Independent
Classifier: Programming Language :: Python :: 3
Classifier: Programming Language :: Python :: 3.10
Classifier: Programming Language :: Python :: 3.11
Classifier: Programming Language :: Python :: 3.12
Classifier: Programming Language :: Python :: 3.13
Classifier: Topic :: System :: Monitoring
Classifier: Topic :: System :: Systems Administration
Project-URL: Homepage, https://github.com/lduchosal/nagioscli
Project-URL: Bug Reports, https://github.com/lduchosal/nagioscli/issues
Project-URL: Source, https://github.com/lduchosal/nagioscli
Project-URL: Documentation, https://github.com/lduchosal/nagioscli/blob/main/README.md
Requires-Python: >=3.10
Requires-Dist: click<9.0,>=8.0
